{
  "gitSyncId": "67249a906d05d410f957f67e_43d7375c-d76f-4603-8342-ba6305e34bab",
  "id": "Login_functions.login",
  "pluginId": "js-plugin",
  "pluginType": "JS",
  "unpublishedAction": {
    "actionConfiguration": {
      "encodeParamsToggle": true,
      "jsArguments": [],
      "paginationType": "NONE",
      "timeoutInMillisecond": 10000
    },
    "collectionId": "Login_functions",
    "confirmBeforeExecute": false,
    "datasource": {
      "isAutoGenerated": false,
      "name": "UNUSED_DATASOURCE",
      "pluginId": "js-plugin"
    },
    "dynamicBindingPathList": [
      {
        "key": "body"
      }
    ],
    "executeOnLoad": false,
    "fullyQualifiedName": "functions.login",
    "name": "login",
    "pageId": "Login",
    "userSetOnLoad": false
  }
}